fairyex/__init__.py
fairyex/darksol.py
fairyex/kernel/__init__.py
fairyex/kernel/querid.py
fairyex/kernel/querxml.py
fairyex/kernel/query.py
fairyex/kernel/queryex.py
fairyex/utils/__init__.py
fairyex/utils/_version.py
fairyex/utils/exceptions.py
fairyex-0.2.1.dist-info/METADATA
fairyex-0.2.1.dist-info/WHEEL
fairyex-0.2.1.dist-info/top_level.txt
fairyex-0.2.1.dist-info/RECORD
