Metadata-Version: 2.4
Name: fairyex
Version: 0.2.1
Summary: FairyEx - FEErical Extraction
Author: Harry Ung
Project-URL: Documentation, https://codacave.gitlab.io/fairyex/
Project-URL: Repository, https://gitlab.com/CodaCave/fairyex
Project-URL: Changelog, https://gitlab.com/CodaCave/fairyex/-/releases
Requires-Python: >=3.10
Requires-Dist: numpy
Requires-Dist: pandas
Requires-Dist: polars
Requires-Dist: pyarrow
